<annotation>
	<folder>Yellow trap 4 last 63</folder>
	<filename>PHOTO-2021-02-24-12-13-48.jpg</filename>
	<path>C:\Users\User\Desktop\Yellow trap 4 last 63\PHOTO-2021-02-24-12-13-48.jpg</path>
	<source>
		<database>Unknown</database>
	</source>
	<size>
		<width>1600</width>
		<height>720</height>
		<depth>3</depth>
	</size>
	<segmented>0</segmented>
	<object>
		<name>DBM</name>
		<pose>Unspecified</pose>
		<truncated>0</truncated>
		<difficult>0</difficult>
		<bndbox>
			<xmin>511</xmin>
			<ymin>474</ymin>
			<xmax>535</xmax>
			<ymax>487</ymax>
		</bndbox>
	</object>
	<object>
		<name>DBM</name>
		<pose>Unspecified</pose>
		<truncated>0</truncated>
		<difficult>0</difficult>
		<bndbox>
			<xmin>526</xmin>
			<ymin>466</ymin>
			<xmax>540</xmax>
			<ymax>484</ymax>
		</bndbox>
	</object>
	<object>
		<name>DBM</name>
		<pose>Unspecified</pose>
		<truncated>0</truncated>
		<difficult>0</difficult>
		<bndbox>
			<xmin>499</xmin>
			<ymin>530</ymin>
			<xmax>520</xmax>
			<ymax>549</ymax>
		</bndbox>
	</object>
	<object>
		<name>DBM</name>
		<pose>Unspecified</pose>
		<truncated>0</truncated>
		<difficult>0</difficult>
		<bndbox>
			<xmin>644</xmin>
			<ymin>521</ymin>
			<xmax>664</xmax>
			<ymax>543</ymax>
		</bndbox>
	</object>
	<object>
		<name>DBM</name>
		<pose>Unspecified</pose>
		<truncated>0</truncated>
		<difficult>0</difficult>
		<bndbox>
			<xmin>616</xmin>
			<ymin>578</ymin>
			<xmax>639</xmax>
			<ymax>603</ymax>
		</bndbox>
	</object>
	<object>
		<name>DBM</name>
		<pose>Unspecified</pose>
		<truncated>0</truncated>
		<difficult>0</difficult>
		<bndbox>
			<xmin>735</xmin>
			<ymin>547</ymin>
			<xmax>754</xmax>
			<ymax>565</ymax>
		</bndbox>
	</object>
	<object>
		<name>DBM</name>
		<pose>Unspecified</pose>
		<truncated>0</truncated>
		<difficult>0</difficult>
		<bndbox>
			<xmin>756</xmin>
			<ymin>560</ymin>
			<xmax>777</xmax>
			<ymax>575</ymax>
		</bndbox>
	</object>
	<object>
		<name>DBM</name>
		<pose>Unspecified</pose>
		<truncated>0</truncated>
		<difficult>0</difficult>
		<bndbox>
			<xmin>610</xmin>
			<ymin>344</ymin>
			<xmax>632</xmax>
			<ymax>364</ymax>
		</bndbox>
	</object>
	<object>
		<name>DBM</name>
		<pose>Unspecified</pose>
		<truncated>0</truncated>
		<difficult>0</difficult>
		<bndbox>
			<xmin>610</xmin>
			<ymin>316</ymin>
			<xmax>632</xmax>
			<ymax>340</ymax>
		</bndbox>
	</object>
	<object>
		<name>DBM</name>
		<pose>Unspecified</pose>
		<truncated>0</truncated>
		<difficult>0</difficult>
		<bndbox>
			<xmin>674</xmin>
			<ymin>327</ymin>
			<xmax>694</xmax>
			<ymax>344</ymax>
		</bndbox>
	</object>
	<object>
		<name>DBM</name>
		<pose>Unspecified</pose>
		<truncated>0</truncated>
		<difficult>0</difficult>
		<bndbox>
			<xmin>667</xmin>
			<ymin>300</ymin>
			<xmax>691</xmax>
			<ymax>317</ymax>
		</bndbox>
	</object>
	<object>
		<name>DBM</name>
		<pose>Unspecified</pose>
		<truncated>0</truncated>
		<difficult>0</difficult>
		<bndbox>
			<xmin>503</xmin>
			<ymin>397</ymin>
			<xmax>531</xmax>
			<ymax>418</ymax>
		</bndbox>
	</object>
	<object>
		<name>DBM</name>
		<pose>Unspecified</pose>
		<truncated>0</truncated>
		<difficult>0</difficult>
		<bndbox>
			<xmin>504</xmin>
			<ymin>419</ymin>
			<xmax>519</xmax>
			<ymax>441</ymax>
		</bndbox>
	</object>
	<object>
		<name>DBM</name>
		<pose>Unspecified</pose>
		<truncated>0</truncated>
		<difficult>0</difficult>
		<bndbox>
			<xmin>475</xmin>
			<ymin>402</ymin>
			<xmax>499</xmax>
			<ymax>424</ymax>
		</bndbox>
	</object>
	<object>
		<name>DBM</name>
		<pose>Unspecified</pose>
		<truncated>0</truncated>
		<difficult>0</difficult>
		<bndbox>
			<xmin>481</xmin>
			<ymin>335</ymin>
			<xmax>499</xmax>
			<ymax>350</ymax>
		</bndbox>
	</object>
	<object>
		<name>DBM</name>
		<pose>Unspecified</pose>
		<truncated>0</truncated>
		<difficult>0</difficult>
		<bndbox>
			<xmin>500</xmin>
			<ymin>350</ymin>
			<xmax>517</xmax>
			<ymax>368</ymax>
		</bndbox>
	</object>
	<object>
		<name>DBM</name>
		<pose>Unspecified</pose>
		<truncated>0</truncated>
		<difficult>0</difficult>
		<bndbox>
			<xmin>564</xmin>
			<ymin>278</ymin>
			<xmax>577</xmax>
			<ymax>295</ymax>
		</bndbox>
	</object>
	<object>
		<name>DBM</name>
		<pose>Unspecified</pose>
		<truncated>0</truncated>
		<difficult>0</difficult>
		<bndbox>
			<xmin>540</xmin>
			<ymin>289</ymin>
			<xmax>561</xmax>
			<ymax>304</ymax>
		</bndbox>
	</object>
	<object>
		<name>DBM</name>
		<pose>Unspecified</pose>
		<truncated>0</truncated>
		<difficult>0</difficult>
		<bndbox>
			<xmin>566</xmin>
			<ymin>238</ymin>
			<xmax>590</xmax>
			<ymax>258</ymax>
		</bndbox>
	</object>
	<object>
		<name>DBM</name>
		<pose>Unspecified</pose>
		<truncated>0</truncated>
		<difficult>0</difficult>
		<bndbox>
			<xmin>615</xmin>
			<ymin>209</ymin>
			<xmax>640</xmax>
			<ymax>224</ymax>
		</bndbox>
	</object>
	<object>
		<name>DBM</name>
		<pose>Unspecified</pose>
		<truncated>0</truncated>
		<difficult>0</difficult>
		<bndbox>
			<xmin>524</xmin>
			<ymin>190</ymin>
			<xmax>553</xmax>
			<ymax>206</ymax>
		</bndbox>
	</object>
	<object>
		<name>DBM</name>
		<pose>Unspecified</pose>
		<truncated>0</truncated>
		<difficult>0</difficult>
		<bndbox>
			<xmin>487</xmin>
			<ymin>229</ymin>
			<xmax>506</xmax>
			<ymax>255</ymax>
		</bndbox>
	</object>
	<object>
		<name>DBM</name>
		<pose>Unspecified</pose>
		<truncated>0</truncated>
		<difficult>0</difficult>
		<bndbox>
			<xmin>474</xmin>
			<ymin>224</ymin>
			<xmax>495</xmax>
			<ymax>240</ymax>
		</bndbox>
	</object>
	<object>
		<name>DBM</name>
		<pose>Unspecified</pose>
		<truncated>0</truncated>
		<difficult>0</difficult>
		<bndbox>
			<xmin>443</xmin>
			<ymin>221</ymin>
			<xmax>471</xmax>
			<ymax>240</ymax>
		</bndbox>
	</object>
	<object>
		<name>DBM</name>
		<pose>Unspecified</pose>
		<truncated>0</truncated>
		<difficult>0</difficult>
		<bndbox>
			<xmin>499</xmin>
			<ymin>205</ymin>
			<xmax>522</xmax>
			<ymax>221</ymax>
		</bndbox>
	</object>
	<object>
		<name>DBM</name>
		<pose>Unspecified</pose>
		<truncated>0</truncated>
		<difficult>0</difficult>
		<bndbox>
			<xmin>536</xmin>
			<ymin>273</ymin>
			<xmax>556</xmax>
			<ymax>289</ymax>
		</bndbox>
	</object>
	<object>
		<name>DBM</name>
		<pose>Unspecified</pose>
		<truncated>0</truncated>
		<difficult>0</difficult>
		<bndbox>
			<xmin>555</xmin>
			<ymin>444</ymin>
			<xmax>586</xmax>
			<ymax>459</ymax>
		</bndbox>
	</object>
	<object>
		<name>DBM</name>
		<pose>Unspecified</pose>
		<truncated>0</truncated>
		<difficult>0</difficult>
		<bndbox>
			<xmin>842</xmin>
			<ymin>169</ymin>
			<xmax>861</xmax>
			<ymax>190</ymax>
		</bndbox>
	</object>
	<object>
		<name>DBM</name>
		<pose>Unspecified</pose>
		<truncated>0</truncated>
		<difficult>0</difficult>
		<bndbox>
			<xmin>796</xmin>
			<ymin>230</ymin>
			<xmax>812</xmax>
			<ymax>251</ymax>
		</bndbox>
	</object>
	<object>
		<name>DBM</name>
		<pose>Unspecified</pose>
		<truncated>0</truncated>
		<difficult>0</difficult>
		<bndbox>
			<xmin>915</xmin>
			<ymin>229</ymin>
			<xmax>930</xmax>
			<ymax>248</ymax>
		</bndbox>
	</object>
	<object>
		<name>DBM</name>
		<pose>Unspecified</pose>
		<truncated>0</truncated>
		<difficult>0</difficult>
		<bndbox>
			<xmin>890</xmin>
			<ymin>445</ymin>
			<xmax>910</xmax>
			<ymax>464</ymax>
		</bndbox>
	</object>
	<object>
		<name>DBM</name>
		<pose>Unspecified</pose>
		<truncated>0</truncated>
		<difficult>0</difficult>
		<bndbox>
			<xmin>971</xmin>
			<ymin>156</ymin>
			<xmax>990</xmax>
			<ymax>181</ymax>
		</bndbox>
	</object>
	<object>
		<name>DBM</name>
		<pose>Unspecified</pose>
		<truncated>0</truncated>
		<difficult>0</difficult>
		<bndbox>
			<xmin>981</xmin>
			<ymin>154</ymin>
			<xmax>1001</xmax>
			<ymax>163</ymax>
		</bndbox>
	</object>
	<object>
		<name>DBM</name>
		<pose>Unspecified</pose>
		<truncated>0</truncated>
		<difficult>0</difficult>
		<bndbox>
			<xmin>1021</xmin>
			<ymin>307</ymin>
			<xmax>1036</xmax>
			<ymax>330</ymax>
		</bndbox>
	</object>
	<object>
		<name>DBM</name>
		<pose>Unspecified</pose>
		<truncated>0</truncated>
		<difficult>0</difficult>
		<bndbox>
			<xmin>989</xmin>
			<ymin>524</ymin>
			<xmax>1011</xmax>
			<ymax>550</ymax>
		</bndbox>
	</object>
	<object>
		<name>DBM</name>
		<pose>Unspecified</pose>
		<truncated>0</truncated>
		<difficult>0</difficult>
		<bndbox>
			<xmin>1057</xmin>
			<ymin>394</ymin>
			<xmax>1083</xmax>
			<ymax>414</ymax>
		</bndbox>
	</object>
	<object>
		<name>DBM</name>
		<pose>Unspecified</pose>
		<truncated>0</truncated>
		<difficult>0</difficult>
		<bndbox>
			<xmin>683</xmin>
			<ymin>274</ymin>
			<xmax>704</xmax>
			<ymax>294</ymax>
		</bndbox>
	</object>
</annotation>